{
  "animateLoading": true,
  "borderRadius": "{{appsmith.theme.borderRadius.appBorderRadius}}",
  "bottomRow": 6,
  "dynamicBindingPathList": [
    {
      "key": "truncateButtonColor"
    },
    {
      "key": "fontFamily"
    },
    {
      "key": "borderRadius"
    }
  ],
  "dynamicHeight": "AUTO_HEIGHT",
  "dynamicTriggerPathList": [],
  "fontFamily": "{{appsmith.theme.fontFamily.appFont}}",
  "fontSize": "1rem",
  "fontStyle": "BOLD",
  "isLoading": false,
  "isVisible": true,
  "key": "8llehhfl2n",
  "leftColumn": 24,
  "maxDynamicHeight": 9000,
  "minDynamicHeight": 4,
  "minWidth": 450,
  "mobileBottomRow": 6,
  "mobileLeftColumn": 24,
  "mobileRightColumn": 40,
  "mobileTopRow": 2,
  "needsErrorInfo": false,
  "originalBottomRow": 6,
  "originalTopRow": 2,
  "overflow": "NONE",
  "parentColumnSpace": 13.30859375,
  "parentId": "2lemxf2rrj",
  "parentRowSpace": 10,
  "renderMode": "CANVAS",
  "responsiveBehavior": "fill",
  "rightColumn": 43,
  "shouldTruncate": false,
  "text": "Choose category\n",
  "textAlign": "LEFT",
  "textColor": "#231F20",
  "topRow": 2,
  "truncateButtonColor": "{{appsmith.theme.colors.primaryColor}}",
  "type": "TEXT_WIDGET",
  "version": 1,
  "widgetId": "j3aiv2pj5c",
  "widgetName": "Text1"
}