{
  "animateLoading": true,
  "borderRadius": "{{appsmith.theme.borderRadius.appBorderRadius}}",
  "bottomRow": 10,
  "boxShadow": "none",
  "buttonColor": "{{appsmith.theme.colors.primaryColor}}",
  "buttonVariant": "PRIMARY",
  "dynamicBindingPathList": [
    {
      "key": "buttonColor"
    },
    {
      "key": "borderRadius"
    }
  ],
  "dynamicTriggerPathList": [
    {
      "key": "onClick"
    }
  ],
  "iconName": "fast-backward",
  "isDisabled": false,
  "isLoading": false,
  "isVisible": true,
  "key": "txqq913lzm",
  "leftColumn": 4,
  "minWidth": 50,
  "mobileBottomRow": 10,
  "mobileLeftColumn": 4,
  "mobileRightColumn": 8,
  "mobileTopRow": 6,
  "needsErrorInfo": false,
  "onClick": "{{navigateTo('Customer_UI', {}, 'SAME_WINDOW');}}",
  "parentColumnSpace": 19.8125,
  "parentId": "0",
  "parentRowSpace": 10,
  "renderMode": "CANVAS",
  "responsiveBehavior": "hug",
  "rightColumn": 8,
  "topRow": 6,
  "type": "ICON_BUTTON_WIDGET",
  "version": 1,
  "widgetId": "ue089x7wke",
  "widgetName": "IconButton1"
}