{
  "gitSyncId": "66a3d9564839614e01725e62_033b173e-ea86-4170-b403-02bb8b3232f9",
  "id": "client_login_functions.register",
  "pluginId": "js-plugin",
  "pluginType": "JS",
  "unpublishedAction": {
    "actionConfiguration": {
      "encodeParamsToggle": true,
      "jsArguments": [],
      "paginationType": "NONE",
      "timeoutInMillisecond": 10000
    },
    "collectionId": "client_login_functions",
    "confirmBeforeExecute": false,
    "datasource": {
      "isAutoGenerated": false,
      "name": "UNUSED_DATASOURCE",
      "pluginId": "js-plugin"
    },
    "dynamicBindingPathList": [
      {
        "key": "body"
      }
    ],
    "executeOnLoad": false,
    "fullyQualifiedName": "functions.register",
    "name": "register",
    "pageId": "client_login",
    "userSetOnLoad": false
  }
}